naturalselection/__init__.py
naturalselection/callbacks.py
naturalselection/core.py
naturalselection/nn.py
naturalselection-0.6.0.dist-info/LICENSE
naturalselection-0.6.0.dist-info/METADATA
naturalselection-0.6.0.dist-info/WHEEL
naturalselection-0.6.0.dist-info/entry_points.txt
naturalselection-0.6.0.dist-info/top_level.txt
naturalselection-0.6.0.dist-info/RECORD
