Metadata-Version: 2.1
Name: naturalselection
Version: 0.6.0
Summary: An all-purpose pythonic genetic algorithm
Home-page: https://github.com/saattrupdan/naturalselection
Author: Dan Saattrup Nielsen
Author-email: saattrupdan@gmail.com
License: UNKNOWN
Keywords: genetic algorithm neural network
Platform: UNKNOWN
Classifier: Development Status :: 3 - Alpha
Classifier: Programming Language :: Python :: 3
Classifier: License :: OSI Approved :: MIT License
Classifier: Operating System :: OS Independent
Requires-Dist: numpy
Requires-Dist: matplotlib
Requires-Dist: tqdm
Requires-Dist: tensorflow
Requires-Dist: sklearn
